CHANGELOG.md
LICENSE
MANIFEST.in
README.md
pyproject.toml
setup.cfg
setup.py
tests/__init__.py
tests/test_videoplayer.py
videoplayer/VideoPlayer.c
videoplayer/VideoPlayer.h
videoplayer/_VideoPlayer.c
videoplayer/_VideoPlayer.pyx
videoplayer/__init__.py
videoplayer/glwrap.h
videoplayer.egg-info/PKG-INFO
videoplayer.egg-info/SOURCES.txt
videoplayer.egg-info/dependency_links.txt
videoplayer.egg-info/not-zip-safe
videoplayer.egg-info/requires.txt
videoplayer.egg-info/top_level.txt