Metadata-Version: 2.1
Name: videoplayer
Version: 1.0
Summary: VideoPlayer is a C-extension in Python
Home-page: https://github.com/fofix/python-videoplayer
Author: FoFiX team
Author-email: fofix@perdu.fr
License: GPLv2+
Keywords: ogg
Platform: UNKNOWN
Classifier: Intended Audience :: Developers
Classifier: License :: OSI Approved :: GNU General Public License v2 or later (GPLv2+)
Classifier: Programming Language :: Python
Classifier: Programming Language :: Python :: 2
Classifier: Programming Language :: Python :: 2.7
Classifier: Programming Language :: Python :: 3
Classifier: Topic :: Multimedia
Classifier: Topic :: Software Development :: Libraries
Provides-Extra: tests
